hello_pratyush1606/hello.py
hello_pratyush1606-1.0.0.dist-info/METADATA
hello_pratyush1606-1.0.0.dist-info/WHEEL
hello_pratyush1606-1.0.0.dist-info/top_level.txt
hello_pratyush1606-1.0.0.dist-info/RECORD
